localsets/__init__.py
localsets/cli.py
localsets/core.py
localsets/formats.py
localsets/smogon.py
localsets/updater.py
localsets/metadata/gen1randombattle_metadata.json
localsets/metadata/gen2randombattle_metadata.json
localsets/metadata/gen3randombattle_metadata.json
localsets/metadata/gen4randombattle_metadata.json
localsets/metadata/gen5randombattle_metadata.json
localsets/metadata/gen6randombattle_metadata.json
localsets/metadata/gen7letsgorandombattle_metadata.json
localsets/metadata/gen7randombattle_metadata.json
localsets/metadata/gen8bdsprandombattle_metadata.json
localsets/metadata/gen8randombattle_metadata.json
localsets/metadata/gen8randomdoublesbattle_metadata.json
localsets/metadata/gen9babyrandombattle_metadata.json
localsets/metadata/gen9randombattle_metadata.json
localsets/metadata/gen9randomdoublesbattle_metadata.json
localsets/randbattle_data/gen1randombattle.json
localsets/randbattle_data/gen2randombattle.json
localsets/randbattle_data/gen3randombattle.json
localsets/randbattle_data/gen4randombattle.json
localsets/randbattle_data/gen5randombattle.json
localsets/randbattle_data/gen6randombattle.json
localsets/randbattle_data/gen7letsgorandombattle.json
localsets/randbattle_data/gen7randombattle.json
localsets/randbattle_data/gen8bdsprandombattle.json
localsets/randbattle_data/gen8randombattle.json
localsets/randbattle_data/gen8randomdoublesbattle.json
localsets/randbattle_data/gen9babyrandombattle.json
localsets/randbattle_data/gen9randombattle.json
localsets/randbattle_data/gen9randomdoublesbattle.json
localsets/smogon_data/gen1nu.json
localsets/smogon_data/gen1ou.json
localsets/smogon_data/gen1pu.json
localsets/smogon_data/gen1ubers.json
localsets/smogon_data/gen1uu.json
localsets/smogon_data/gen2nu.json
localsets/smogon_data/gen2ou.json
localsets/smogon_data/gen2pu.json
localsets/smogon_data/gen2ubers.json
localsets/smogon_data/gen2uu.json
localsets/smogon_data/gen3doublesou.json
localsets/smogon_data/gen3nu.json
localsets-0.1.71.dist-info/licenses/LICENSE
localsets-0.1.71.dist-info/METADATA
localsets-0.1.71.dist-info/WHEEL
localsets-0.1.71.dist-info/entry_points.txt
localsets-0.1.71.dist-info/top_level.txt
localsets-0.1.71.dist-info/RECORD
