Metadata-Version: 2.4
Name: localsets
Version: 0.1.71
Summary: Local Pokemon random battle sets (auto-updating) and Smogon competitive sets
License: MIT
Project-URL: Homepage, https://github.com/colefoster/localsets
Project-URL: Repository, https://github.com/colefoster/localsets
Project-URL: Documentation, https://github.com/colefoster/localsets#readme
Keywords: pokemon,battle,data,random,showdown,smogon,competitive
Classifier: Development Status :: 4 - Beta
Classifier: Intended Audience :: Developers
Classifier: License :: OSI Approved :: MIT License
Classifier: Programming Language :: Python :: 3
Classifier: Programming Language :: Python :: 3.8
Classifier: Programming Language :: Python :: 3.9
Classifier: Programming Language :: Python :: 3.10
Classifier: Programming Language :: Python :: 3.11
Classifier: Programming Language :: Python :: 3.12
Classifier: Topic :: Games/Entertainment
Classifier: Topic :: Software Development :: Libraries :: Python Modules
Requires-Python: >=3.8
License-File: LICENSE
Requires-Dist: requests>=2.25.0
Requires-Dist: appdirs>=1.4.0
Provides-Extra: no-cli
Provides-Extra: dev
Requires-Dist: pytest>=6.0.0; extra == "dev"
Requires-Dist: pytest-cov>=2.10.0; extra == "dev"
Requires-Dist: black>=21.0.0; extra == "dev"
Requires-Dist: flake8>=3.8.0; extra == "dev"
Requires-Dist: mypy>=0.800; extra == "dev"
Requires-Dist: twine>=3.0.0; extra == "dev"
Requires-Dist: wheel>=0.36.0; extra == "dev"
Dynamic: license-file
